diarybot/__init__.py
diarybot/bot.py
diarybot/bot_config.py
diarybot/cli.py
diarybot/dgit.py
diarybot/dispatcher.py
diarybot/events.py
diarybot/guest.py
diarybot/installer.py
diarybot/interface.py
diarybot/receiver.py
diarybot/skill_interface.py
diarybot/skills.py
diarybot/ssh.sh
diarybot/tenant.py
diarybot/tenant_config.py
diarybot/core/__init__.py
diarybot/core/buy_list.py
diarybot/core/git_sync.py
diarybot/core/journal.py
diarybot/core/recorder.py
diarybot/core/speech_to_text.py
diarybot/core/text_handler.py
diarybot/extractors/__init__.py
diarybot/extractors/extractor.py
diarybot/extractors/interface.py
diarybot/extractors/location.py
diarybot/extractors/photo.py
diarybot/extractors/text.py
diarybot/extractors/voice.py
diarybot/handlers/__init__.py
diarybot/handlers/interface.py
diarybot/handlers/loader.py
diarybot/handlers/location.py
diarybot/handlers/photo.py
diarybot/handlers/text.py
diarybot/handlers/voice.py
diarybot/transformers/__init__.py
diarybot/transformers/base_media.py
diarybot/transformers/location.py
diarybot/transformers/photo.py
diarybot/transformers/voice.py
GitDiaryBot-0.0.1.dist-info/METADATA
GitDiaryBot-0.0.1.dist-info/WHEEL
GitDiaryBot-0.0.1.dist-info/entry_points.txt
GitDiaryBot-0.0.1.dist-info/top_level.txt
GitDiaryBot-0.0.1.dist-info/RECORD
