Metadata-Version: 2.1
Name: GitDiaryBot
Version: 0.0.1
Summary: Diary bot using git repo as a primary storage
Home-page: https://github.com/peterdemin/GitDiaryBot
Author: Peter Demin
Author-email: peterdemin@gmail.com
License: MIT license
Keywords: git diary bot
Platform: UNKNOWN
Classifier: Development Status :: 4 - Beta
Classifier: Intended Audience :: Developers
Classifier: License :: OSI Approved :: MIT License
Classifier: Natural Language :: English
Classifier: Programming Language :: Python :: 3.6
Classifier: Programming Language :: Python :: 3.7
Requires-Dist: GitPython
Requires-Dist: python-telegram-bot
Requires-Dist: tzlocal
Requires-Dist: attrs
Requires-Dist: requests
